cushy_storage/__init__.py
cushy_storage/_core.py
cushy_storage/base.py
cushy_storage/orm.py
cushy_storage/utils/__init__.py
cushy_storage/utils/logger.py
cushy_storage/utils/singleton.py
cushy_storage-1.3.8.dist-info/LICENSE
cushy_storage-1.3.8.dist-info/METADATA
cushy_storage-1.3.8.dist-info/WHEEL
cushy_storage-1.3.8.dist-info/RECORD
