Metadata-Version: 2.1
Name: cushy-storage
Version: 1.3.8
Summary: A data local persistence ORM framework.
Home-page: https://github.com/Undertone0809/cushy-storage
Keywords: storage,ORM,serialization,json,cushy-storage,cushy_storage
Author: Zeeland
Author-email: zeeland4work@gmail.com
Requires-Python: >=3.8,<4.0
Classifier: Programming Language :: Python :: 3
Classifier: Programming Language :: Python :: 3.8
Classifier: Programming Language :: Python :: 3.9
Classifier: Programming Language :: Python :: 3.10
Classifier: Programming Language :: Python :: 3.11
Classifier: Programming Language :: Python :: 3.12
Project-URL: Repository, https://github.com/Undertone0809/cushy-storage
